srv/__init__.py
srv/__main__.py
srv/srv.py
srv/templates/directory.html
srv-1.1.0.dist-info/LICENSE
srv-1.1.0.dist-info/METADATA
srv-1.1.0.dist-info/WHEEL
srv-1.1.0.dist-info/entry_points.txt
srv-1.1.0.dist-info/top_level.txt
srv-1.1.0.dist-info/RECORD
